checksum/__init__.py
checksum/__main__.py
checksum/checksum.py
checksum_Pmk456-2.1.dist-info/LICENSE
checksum_Pmk456-2.1.dist-info/METADATA
checksum_Pmk456-2.1.dist-info/WHEEL
checksum_Pmk456-2.1.dist-info/top_level.txt
checksum_Pmk456-2.1.dist-info/RECORD
