Metadata-Version: 2.1
Name: checksum-Pmk456
Version: 2.1
Summary: Checksum Is Used For checking File Integrity And Matching With Given Hashes
Home-page: https://github.com/pmk456/checksum
Author: Patan Musthakheem
Author-email: patanmusthakheem786@gmail.com
License: UNKNOWN
Project-URL: Bug Tracker, https://github.com/pmk456/checksumissues
Platform: UNKNOWN
Classifier: Programming Language :: Python :: 3
Classifier: License :: OSI Approved :: MIT License
Classifier: Operating System :: OS Independent
Requires-Python: >=3.6
